agentz/agent/base.py
agentz/artifacts/__init__.py
agentz/artifacts/artifact_writer.py
agentz/artifacts/reporter.py
agentz/artifacts/terminal_writer.py
agentz/context/__init__.py
agentz/context/context.py
agentz/context/conversation.py
agentz/context/data_store.py
agentz/llm/llm_setup.py
agentz/mcp/manager.py
agentz/mcp/patches.py
agentz/mcp/servers/chrome_devtools/server.py
agentz/profiles/base.py
agentz/profiles/data/data_analysis.py
agentz/profiles/data/data_loader.py
agentz/profiles/data/evaluation.py
agentz/profiles/data/model_training.py
agentz/profiles/data/preprocessing.py
agentz/profiles/data/visualization.py
agentz/profiles/manager/evaluate.py
agentz/profiles/manager/memory.py
agentz/profiles/manager/observe.py
agentz/profiles/manager/routing.py
agentz/profiles/manager/writer.py
agentz/profiles/mcp/browser.py
agentz/profiles/mcp/chrome.py
agentz/profiles/mcp/notion.py
agentz/runner/__init__.py
agentz/runner/base.py
agentz/runner/executor.py
agentz/runner/hooks.py
agentz/runner/iteration.py
agentz/runner/patterns.py
agentz/runner/tracker.py
agentz/runner/utils.py
agentz/runner/workflow.py
agentz/tools/__init__.py
agentz/tools/data_tools/__init__.py
agentz/tools/data_tools/data_analysis.py
agentz/tools/data_tools/data_loading.py
agentz/tools/data_tools/evaluation.py
agentz/tools/data_tools/helpers.py
agentz/tools/data_tools/model_training.py
agentz/tools/data_tools/preprocessing.py
agentz/tools/data_tools/visualization.py
agentz/utils/__init__.py
agentz/utils/config.py
agentz/utils/helpers.py
agentz/utils/parsers.py
agentz/utils/printer.py
pipelines/base.py
pipelines/data_scientist.py
pipelines/data_scientist_memory.py
pipelines/experience_learner.py
pipelines/prompt_generator.py
pipelines/simple.py
pipelines/simple_browser.py
pipelines/simple_chrome.py
pipelines/simple_notion.py
pipelines/tool_builder.py
zero_agent-0.1.0.dist-info/licenses/LICENSE
zero_agent-0.1.0.dist-info/METADATA
zero_agent-0.1.0.dist-info/WHEEL
zero_agent-0.1.0.dist-info/top_level.txt
zero_agent-0.1.0.dist-info/RECORD
